Workbook

Sheet Panel Principal
B1: 2025 | C1: 2025 | D1: 2025 | E1: 2025 | F1: 2025 | G1: 2025 | H1: 2025 | I1: 2025 | J1: 2025 | K1: 2025 | L1: 2026 | M1: 2026 | N1: 2026 | O1: 2026 | P1: 2026 | Q1: 2026 | R1: 2026 | S1: 2026 | T1: 2026 | U1: 2026 | V1: 2026 | W1: 2026 | X1: 2027 | Y1: 2027 | Z1: 2027 | AA1: 2027 | AB1: 2027 | AC1: 2027 | AD1: 2027 | AE1: 2027 | AF1: 2027 | AG1: 2027 | AH1: 2027 | AI1: 2027 | AJ1: 2028 | AK1: 2028 | AL1: 2028 | AM1: 2028 | AN1: 2028 | AO1: 2028 | AP1: 2028 | AQ1: 2028 | AR1: 2028 | AS1: 2028
B2: Marzo 2025 | C2: Abril 2025 | D2: Mayo 2025 | E2: Junio 2025 | F2: Julio 2025 | G2: Agosto 2025 | H2: Septiembre 2025 | I2: Octubre 2025 | J2: Noviembre 2025 | K2: Diciembre 2025 | L2: Enero 2026 | M2: Febrero 2026 | N2: Marzo 2026 | O2: Abril 2026 | P2: Mayo 2026 | Q2: Junio 2026 | R2: Julio 2026 | S2: Agosto 2026 | T2: Septiembre 2026 | U2: Octubre 2026 | V2: Noviembre 2026 | W2: Diciembre 2026 | X2: Enero 2027 | Y2: Febrero 2027 | Z2: Marzo 2027 | AA2: Abril 2027 | AB2: Mayo 2027 | AC2: Junio 2027 | AD2: Julio 2027 | AE2: Agosto 2027 | AF2: Septiembre 2027 | AG2: Octubre 2027 | AH2: Noviembre 2027 | AI2: Diciembre 2027 | AJ2: Enero 2028 | AK2: Febrero 2028 | AL2: Marzo 2028 | AM2: Abril 2028 | AN2: Mayo 2028 | AO2: Junio 2028 | AP2: Julio 2028 | AQ2: Agosto 2028 | AR2: Septiembre 2028 | AS2: Octubre 2028
A3: 📊 RESUMEN DE GASTOS
A4: Tarjetas & Bancos | B4: =Tarjetas_Bancos!B13 -> -2307584 | C4: =Tarjetas_Bancos!C13 -> -1341061.7 | D4: =Tarjetas_Bancos!D13 -> -2287461.7 | E4: =Tarjetas_Bancos!E13 -> -2689870 | F4: =Tarjetas_Bancos!F13 -> -2153870 | G4: =Tarjetas_Bancos!G13 -> -2806870 | H4: =Tarjetas_Bancos!H13 -> -6759277 | I4: =Tarjetas_Bancos!I13 -> -1860000 | ... AS4: =Tarjetas_Bancos!AS13 -> 0
A5: Gastos Personales | B5: =Gastos_Personales!B11 -> 0 | C5: =Gastos_Personales!C11 -> 0 | D5: =Gastos_Personales!D11 -> 0 | E5: =Gastos_Personales!E11 -> 0 | F5: =Gastos_Personales!F11 -> 0 | G5: =Gastos_Personales!G11 -> 0 | H5: =Gastos_Personales!H11 -> 0 | I5: =Gastos_Personales!I11 -> -70000 | ... AS5: =Gastos_Personales!AS11 -> 0
A6: Hogar | B6: =Hogar!B16 -> 0 | C6: =Hogar!C16 -> 0 | D6: =Hogar!D16 -> 0 | E6: =Hogar!E16 -> -24000 | F6: =Hogar!F16 -> -627000 | G6: =Hogar!G16 -> -611200 | H6: =Hogar!H16 -> -810800 | I6: =Hogar!I16 -> -822060 | ... AS6: =Hogar!AS16 -> 0
A7: Deudas & Varios | B7: =Deudas_Varios!B11 -> 0 | C7: =Deudas_Varios!C11 -> 0 | D7: =Deudas_Varios!D11 -> 0 | E7: =Deudas_Varios!E11 -> 0 | F7: =Deudas_Varios!F11 -> -760000 | G7: =Deudas_Varios!G11 -> 0 | H7: =Deudas_Varios!H11 -> 0 | I7: =Deudas_Varios!I11 -> 0 | ... AS7: =Deudas_Varios!AS11 -> 0
A8: TOTAL GASTOS | B8: =SUM(B4:B7) -> -2307584 | C8: =SUM(C4:C7) -> -1341061.7 | D8: =SUM(D4:D7) -> -2287461.7 | E8: =SUM(E4:E7) -> -2713870 | F8: =SUM(F4:F7) -> -3540870 | G8: =SUM(G4:G7) -> -3418070 | H8: =SUM(H4:H7) -> -7570077 | I8: =SUM(I4:I7) -> -2752060 | ... AS8: =SUM(AS4:AS7) -> 0
A9: 💰 INGRESOS
A10: Ingresos Totales | B10: =Ingresos!B11 -> 1100000 | C10: =Ingresos!C11 -> 1100000 | D10: =Ingresos!D11 -> 1100000 | E10: =Ingresos!E11 -> 1230000 | F10: =Ingresos!F11 -> 1760000 | G10: =Ingresos!G11 -> 1215000 | H10: =Ingresos!H11 -> 7225000 | I10: =Ingresos!I11 -> 1285000 | ... AS10: =Ingresos!AS11 -> 0
A11: ¿LLEGAMOS A PAGAR? | B11: =B10+B8 -> -1207584 | C11: =C10+C8 -> -241061.69 | D11: =D10+D8 -> -1187461.7 | E11: =E10+E8 -> -1483870 | F11: =F10+F8 -> -1780870 | G11: =G10+G8 -> -2203070 | H11: =H10+H8 -> -345077 | I11: =I10+I8 -> -1467060 | ... AS11: =AS10+AS8 -> 0

Sheet Ingresos
B1: 2025 | C1: 2025 | D1: 2025 | E1: 2025 | F1: 2025 | G1: 2025 | H1: 2025 | I1: 2025 | J1: 2025 | K1: 2025 | L1: 2026 | M1: 2026 | N1: 2026 | O1: 2026 | P1: 2026 | Q1: 2026 | R1: 2026 | S1: 2026 | T1: 2026 | U1: 2026 | V1: 2026 | W1: 2026 | X1: 2027 | Y1: 2027 | Z1: 2027 | AA1: 2027 | AB1: 2027 | AC1: 2027 | AD1: 2027 | AE1: 2027 | AF1: 2027 | AG1: 2027 | AH1: 2027 | AI1: 2027 | AJ1: 2028 | AK1: 2028 | AL1: 2028 | AM1: 2028 | AN1: 2028 | AO1: 2028 | AP1: 2028 | AQ1: 2028 | AR1: 2028 | AS1: 2028
B2: Marzo 2025 | C2: Abril 2025 | D2: Mayo 2025 | E2: Junio 2025 | F2: Julio 2025 | G2: Agosto 2025 | H2: Septiembre 2025 | I2: Octubre 2025 | J2: Noviembre 2025 | K2: Diciembre 2025 | L2: Enero 2026 | M2: Febrero 2026 | N2: Marzo 2026 | O2: Abril 2026 | P2: Mayo 2026 | Q2: Junio 2026 | R2: Julio 2026 | S2: Agosto 2026 | T2: Septiembre 2026 | U2: Octubre 2026 | V2: Noviembre 2026 | W2: Diciembre 2026 | X2: Enero 2027 | Y2: Febrero 2027 | Z2: Marzo 2027 | AA2: Abril 2027 | AB2: Mayo 2027 | AC2: Junio 2027 | AD2: Julio 2027 | AE2: Agosto 2027 | AF2: Septiembre 2027 | AG2: Octubre 2027 | AH2: Noviembre 2027 | AI2: Diciembre 2027 | AJ2: Enero 2028 | AK2: Febrero 2028 | AL2: Marzo 2028 | AM2: Abril 2028 | AN2: Mayo 2028 | AO2: Junio 2028 | AP2: Julio 2028 | AQ2: Agosto 2028 | AR2: Septiembre 2028 | AS2: Octubre 2028
A3: 💰 INGRESOS
A4: Sueldo de Franco | B4: 1100000 | C4: 1100000 | D4: 1100000 | E4: 1200000 | F4: 1200000 | G4: 1200000 | H4: 1160000 | I4: 1170000 | J4: 1250000 | K4: 1200000 | L4: 1250000 | M4: 1432000 | N4: 1350000 | O4: 1450000 | P4: 1400000 | Q4: 1620000 | R4: 1542000 | S4: 1540000 | T4: 1810000 | U4: 1599000 | V4: 1655000 | W4: 1655000 | X4: 1655000 | Y4: 1655000 | Z4: 1655000 | AA4: 1655000 | AB4: 1655000 | AC4: 1655000 | AD4: 1655000 | AE4: 1655000 | AF4: 1655000 | AG4: 1655000 | AH4: 1655000 | AI4: 1655000 | AJ4: 0 | AK4: 0 | AL4: 0 | AM4: 0 | AN4: 0 | AO4: 0 | AP4: 0 | AQ4: 0 | AR4: 0 | AS4: 0
A5: Sueldo de Abigail | B5: 0 | C5: 0 | D5: 0 | E5: 30000 | F5: 30000 | G5: 0 | H5: 50000 | I5: 100000 | J5: 0 | K5: 0 | L5: 320000 | M5: 960000 | N5: 1400000 | O5: 0 | P5: 0 | Q5: 900000 | R5: 900000 | S5: 950000 | T5: 950000 | U5: 900000 | V5: 1250000 | W5: 1250000 | X5: 1250000 | Y5: 1250000 | Z5: 1250000 | AA5: 1250000 | AB5: 1250000 | AC5: 1250000 | AD5: 1250000 | AE5: 1250000 | AF5: 1250000 | AG5: 1250000 | AH5: 1250000 | AI5: 1250000 | AJ5: 0 | AK5: 0 | AL5: 0 | AM5: 0 | AN5: 0 | AO5: 0 | AP5: 0 | AQ5: 0 | AR5: 0 | AS5: 0
A6: Aguinaldo Franco | B6: 0 | C6: 0 | D6: 0 | E6: 0 | F6: 500000 | G6: 0 | H6: 0 | I6: 0 | J6: 0 | L6: 665000 | M6: 0 | N6: 0 | O6: 0 | P6: 0 | Q6: 0 | R6: 860000 | S6: 0 | T6: 0 | U6: 0 | V6: 0 | W6: 0 | X6: 850000 | Y6: 0 | Z6: 0 | AA6: 0 | AB6: 0 | AC6: 0 | AD6: 850000 | AE6: 0 | AF6: 0 | AG6: 0 | AH6: 0 | AI6: 0 | AJ6: 0 | AK6: 0 | AL6: 0 | AM6: 0 | AN6: 0 | AO6: 0 | AP6: 0 | AQ6: 0 | AR6: 0 | AS6: 0
A7: Aguinaldo Abigail | B7: 0 | C7: 0 | D7: 0 | E7: 0 | F7: 0 | G7: 0 | H7: 0 | I7: 0 | J7: 0 | K7: 0 | L7: 0 | M7: 0 | N7: 0 | O7: 0 | P7: 0 | Q7: 0 | R7: 145000 | S7: 0 | T7: 0 | U7: 0 | V7: 0 | W7: 0 | X7: 250000 | Y7: 0 | Z7: 0 | AA7: 0 | AB7: 0 | AC7: 0 | AD7: 625000 | AE7: 0 | AF7: 0 | AG7: 0 | AH7: 0 | AI7: 0 | AJ7: 0 | AK7: 0 | AL7: 0 | AM7: 0 | AN7: 0 | AO7: 0 | AP7: 0 | AQ7: 0 | AR7: 0 | AS7: 0
A8: Pago de negocio | B8: 0 | C8: 0 | D8: 0 | E8: 0 | F8: 0 | G8: 0 | H8: 6000000 | I8: 0 | J8: 0 | K8: 0 | L8: 0 | M8: 0 | N8: 0 | O8: 0 | P8: 0 | Q8: 0 | R8: 0 | S8: 0 | T8: 0 | U8: 0 | V8: 0 | W8: 0 | X8: 0 | Y8: 0 | Z8: 0 | AA8: 0 | AB8: 0 | AC8: 0 | AD8: 0 | AE8: 0 | AF8: 0 | AG8: 0 | AH8: 0 | AI8: 0 | AJ8: 0 | AK8: 0 | AL8: 0 | AM8: 0 | AN8: 0 | AO8: 0 | AP8: 0 | AQ8: 0 | AR8: 0 | AS8: 0
A9: Ingreso por rendimientos | B9: 0 | C9: 0 | D9: 0 | E9: 0 | F9: 0 | G9: 0 | H9: 0 | I9: 0 | J9: 0 | K9: 0 | L9: 0 | M9: 0 | N9: 0 | O9: 0 | P9: 0 | Q9: 0 | R9: 0 | S9: 0 | T9: 0 | U9: 0 | V9: 0 | W9: 0 | X9: 0 | Y9: 0 | Z9: 0 | AA9: 0 | AB9: 0 | AC9: 0 | AD9: 0 | AE9: 0 | AF9: 0 | AG9: 0 | AH9: 0 | AI9: 0 | AJ9: 0 | AK9: 0 | AL9: 0 | AM9: 0 | AN9: 0 | AO9: 0 | AP9: 0 | AQ9: 0 | AR9: 0 | AS9: 0
A10: Nos deben | B10: 0 | C10: 0 | D10: 0 | E10: 0 | F10: 30000 | G10: 15000 | H10: 15000 | I10: 15000 | J10: 15000 | K10: 15000 | L10: 0 | M10: 0 | N10: 0 | O10: 0 | P10: 0 | Q10: 0 | R10: 0 | S10: 0 | T10: 0 | U10: 0 | V10: 0 | W10: 0 | X10: 0 | Y10: 0 | Z10: 0 | AA10: 0 | AB10: 0 | AC10: 0 | AD10: 0 | AE10: 0 | AF10: 0 | AG10: 0 | AH10: 0 | AI10: 0 | AJ10: 0 | AK10: 0 | AL10: 0 | AM10: 0 | AN10: 0 | AO10: 0 | AP10: 0 | AQ10: 0 | AR10: 0 | AS10: 0
A11: TOTAL | B11: =SUM(B4:B10) -> 1100000 | C11: =SUM(C4:C10) -> 1100000 | D11: =SUM(D4:D10) -> 1100000 | E11: =SUM(E4:E10) -> 1230000 | F11: =SUM(F4:F10) -> 1760000 | G11: =SUM(G4:G10) -> 1215000 | H11: =SUM(H4:H10) -> 7225000 | I11: =SUM(I4:I10) -> 1285000 | ... AS11: =SUM(AS4:AS10) -> 0

Sheet Tarjetas_Bancos
B1: 2025 | C1: 2025 | D1: 2025 | E1: 2025 | F1: 2025 | G1: 2025 | H1: 2025 | I1: 2025 | J1: 2025 | K1: 2025 | L1: 2026 | M1: 2026 | N1: 2026 | O1: 2026 | P1: 2026 | Q1: 2026 | R1: 2026 | S1: 2026 | T1: 2026 | U1: 2026 | V1: 2026 | W1: 2026 | X1: 2027 | Y1: 2027 | Z1: 2027 | AA1: 2027 | AB1: 2027 | AC1: 2027 | AD1: 2027 | AE1: 2027 | AF1: 2027 | AG1: 2027 | AH1: 2027 | AI1: 2027 | AJ1: 2028 | AK1: 2028 | AL1: 2028 | AM1: 2028 | AN1: 2028 | AO1: 2028 | AP1: 2028 | AQ1: 2028 | AR1: 2028 | AS1: 2028
B2: Marzo 2025 | C2: Abril 2025 | D2: Mayo 2025 | E2: Junio 2025 | F2: Julio 2025 | G2: Agosto 2025 | H2: Septiembre 2025 | I2: Octubre 2025 | J2: Noviembre 2025 | K2: Diciembre 2025 | L2: Enero 2026 | M2: Febrero 2026 | N2: Marzo 2026 | O2: Abril 2026 | P2: Mayo 2026 | Q2: Junio 2026 | R2: Julio 2026 | S2: Agosto 2026 | T2: Septiembre 2026 | U2: Octubre 2026 | V2: Noviembre 2026 | W2: Diciembre 2026 | X2: Enero 2027 | Y2: Febrero 2027 | Z2: Marzo 2027 | AA2: Abril 2027 | AB2: Mayo 2027 | AC2: Junio 2027 | AD2: Julio 2027 | AE2: Agosto 2027 | AF2: Septiembre 2027 | AG2: Octubre 2027 | AH2: Noviembre 2027 | AI2: Diciembre 2027 | AJ2: Enero 2028 | AK2: Febrero 2028 | AL2: Marzo 2028 | AM2: Abril 2028 | AN2: Mayo 2028 | AO2: Junio 2028 | AP2: Julio 2028 | AQ2: Agosto 2028 | AR2: Septiembre 2028 | AS2: Octubre 2028
A3: 💳 TARJETAS & BANCOS
A4: Banco BBVA | B4: -1081714 | C4: -751591.69 | D4: -751591.69 | E4: -1360000 | F4: -1083000 | G4: -1450000 | H4: -1695000 | I4: -1300000 | J4: -1733000 | K4: -1450000 | L4: -400000 | M4: -400000 | N4: -400000 | O4: -155000 | P4: -370000 | Q4: -528000 | R4: -700000 | S4: -650000 | T4: -600000 | U4: -700000 | V4: -400000 | W4: 0 | X4: 0 | Y4: 0 | Z4: 0 | AA4: 0 | AB4: 0 | AC4: 0 | AD4: 0 | AE4: 0 | AF4: 0 | AG4: 0 | AH4: 0 | AI4: 0 | AJ4: 0 | AK4: 0 | AL4: 0 | AM4: 0 | AN4: 0 | AO4: 0 | AP4: 0 | AQ4: 0 | AR4: 0 | AS4: 0
A5: Banco Mercado Pago | B5: -149000 | C5: -149000 | D5: -149000 | E5: -149000 | F5: -128000 | G5: -474000 | H5: -502000 | I5: 0 | J5: -161000 | K5: -161000 | L5: -161000 | M5: -161000 | N5: -161000 | O5: -161000 | P5: -161000 | Q5: 0 | R5: 0 | S5: 0 | T5: 0 | U5: 0 | V5: 0 | W5: 0 | X5: 0 | Y5: 0 | Z5: 0 | AA5: 0 | AB5: 0 | AC5: 0 | AD5: 0 | AE5: 0 | AF5: 0 | AG5: 0 | AH5: 0 | AI5: 0 | AJ5: 0 | AK5: 0 | AL5: 0 | AM5: 0 | AN5: 0 | AO5: 0 | AP5: 0 | AQ5: 0 | AR5: 0 | AS5: 0
A6: Préstamo BBVA | B6: -202870 | C6: -202870 | D6: -202870 | E6: -202870 | F6: -202870 | G6: -202870 | H6: -3862277 | I6: 0 | J6: 0 | K6: 0 | L6: 0 | M6: 0 | N6: 0 | O6: 0 | P6: 0 | Q6: 0 | R6: 0 | S6: 0 | T6: 0 | U6: 0 | V6: 0 | W6: 0 | X6: 0 | Y6: 0 | Z6: 0 | AA6: 0 | AB6: 0 | AC6: 0 | AD6: 0 | AE6: 0 | AF6: 0 | AG6: 0 | AH6: 0 | AI6: 0 | AJ6: 0 | AK6: 0 | AL6: 0 | AM6: 0 | AN6: 0 | AO6: 0 | AP6: 0 | AQ6: 0 | AR6: 0 | AS6: 0
A7: Préstamo Naranja X | B7: 0 | C7: -83000 | D7: -83000 | E7: -83000 | F7: 0 | G7: 0 | H7: 0 | I7: 0 | J7: 0 | K7: 0 | L7: 0 | M7: 0 | N7: 0 | O7: 0 | P7: 0 | Q7: 0 | R7: 0 | S7: 0 | T7: 0 | U7: 0 | V7: 0 | W7: 0 | X7: 0 | Y7: 0 | Z7: 0 | AA7: 0 | AB7: 0 | AC7: 0 | AD7: 0 | AE7: 0 | AF7: 0 | AG7: 0 | AH7: 0 | AI7: 0 | AJ7: 0 | AK7: 0 | AL7: 0 | AM7: 0 | AN7: 0 | AO7: 0 | AP7: 0 | AQ7: 0 | AR7: 0 | AS7: 0
A8: Banco Naranja X | B8: -840000 | C8: -120600 | D8: -1067000 | E8: -895000 | F8: -740000 | G8: -680000 | H8: -700000 | I8: -560000 | J8: -850000 | K8: -1000000 | L8: -600000 | M8: -127000 | N8: -193000 | O8: -139000 | P8: -139000 | Q8: -139000 | R8: -139000 | S8: -139000 | T8: -143000 | U8: -143000 | V8: -143000 | W8: -143000 | X8: -143000 | Y8: -143000 | Z8: -143000 | AA8: -143000 | AB8: -143000 | AC8: -143000 | AD8: -143000 | AE8: -143000 | AF8: -143000 | AG8: -143000 | AH8: -143000 | AI8: -143000 | AJ8: 0 | AK8: 0 | AL8: 0 | AM8: 0 | AN8: 0 | AO8: 0 | AP8: 0 | AQ8: 0 | AR8: 0 | AS8: 0
A9: Banco Santander | B9: -34000 | C9: -34000 | D9: -34000 | E9: 0 | F9: 0 | G9: 0 | H9: 0 | I9: 0 | J9: 0 | K9: 0 | L9: 0 | M9: 0 | N9: 0 | O9: 0 | P9: 0 | Q9: 0 | R9: 0 | S9: 0 | T9: 0 | U9: 0 | V9: 0 | W9: 0 | X9: 0 | Y9: 0 | Z9: 0 | AA9: 0 | AB9: 0 | AC9: 0 | AD9: 0 | AE9: 0 | AF9: 0 | AG9: 0 | AH9: 0 | AI9: 0 | AJ9: 0 | AK9: 0 | AL9: 0 | AM9: 0 | AN9: 0 | AO9: 0 | AP9: 0 | AQ9: 0 | AR9: 0 | AS9: 0
A10: Banco BNA (Franco) | B10: 0 | C10: 0 | D10: 0 | E10: 0 | F10: 0 | G10: 0 | H10: 0 | I10: 0 | J10: 0 | K10: 0 | L10: 0 | M10: -250000 | N10: -170000 | O10: -70000 | P10: -137000 | Q10: -160000 | R10: -375000 | S10: -50000 | T10: -150000 | U10: -16000 | V10: 0 | W10: 0 | X10: 0 | Y10: 0 | Z10: 0 | AA10: 0 | AB10: 0 | AC10: 0 | AD10: 0 | AE10: 0 | AF10: 0 | AG10: 0 | AH10: 0 | AI10: 0 | AJ10: 0 | AK10: 0 | AL10: 0 | AM10: 0 | AN10: 0 | AO10: 0 | AP10: 0 | AQ10: 0 | AR10: 0 | AS10: 0
A11: Banco BNA (Abi) | B11: 0 | C11: 0 | D11: 0 | E11: 0 | F11: 0 | G11: 0 | H11: 0 | I11: 0 | J11: 0 | K11: 0 | L11: 0 | M11: 0 | N11: -200000 | O11: -50000 | P11: -37000 | Q11: 0 | R11: - | S11: - | T11: -140000 | U11: -160000 | W11: 0 | X11: 0 | Y11: 0 | Z11: 0 | AA11: 0 | AB11: 0 | AC11: 0 | AD11: 0 | AE11: 0 | AF11: 0 | AG11: 0 | AH11: 0 | AI11: 0 | AJ11: 0 | AK11: 0 | AL11: 0 | AM11: 0 | AN11: 0 | AO11: 0 | AP11: 0 | AQ11: 0 | AR11: 0 | AS11: 0
A12: GO Cuotas (Abi) | B12: 0 | C12: 0 | D12: 0 | E12: 0 | F12: 0 | G12: 0 | H12: 0 | I12: 0 | J12: 0 | K12: 0 | L12: 0 | M12: 0 | N12: 0 | O12: 0 | P12: 0 | Q12: -70000 | R12: 0 | S12: 0 | T12: 0 | U12: 0 | V12: 0 | W12: 0 | X12: 0 | Y12: 0 | Z12: 0 | AA12: 0 | AB12: 0 | AC12: 0 | AD12: 0 | AE12: 0 | AF12: 0 | AG12: 0 | AH12: 0 | AI12: 0 | AJ12: 0 | AK12: 0 | AL12: 0 | AM12: 0 | AN12: 0 | AO12: 0 | AP12: 0 | AQ12: 0 | AR12: 0 | AS12: 0
A13: TOTAL | B13: =SUM(B4:B12) -> -2307584 | C13: =SUM(C4:C12) -> -1341061.7 | D13: =SUM(D4:D12) -> -2287461.7 | E13: =SUM(E4:E12) -> -2689870 | F13: =SUM(F4:F12) -> -2153870 | G13: =SUM(G4:G12) -> -2806870 | H13: =SUM(H4:H12) -> -6759277 | I13: =SUM(I4:I12) -> -1860000 | ... AS13: =SUM(AS4:AS12) -> 0

Sheet Gastos_Personales
B1: 2025 | C1: 2025 | D1: 2025 | E1: 2025 | F1: 2025 | G1: 2025 | H1: 2025 | I1: 2025 | J1: 2025 | K1: 2025 | L1: 2026 | M1: 2026 | N1: 2026 | O1: 2026 | P1: 2026 | Q1: 2026 | R1: 2026 | S1: 2026 | T1: 2026 | U1: 2026 | V1: 2026 | W1: 2026 | X1: 2027 | Y1: 2027 | Z1: 2027 | AA1: 2027 | AB1: 2027 | AC1: 2027 | AD1: 2027 | AE1: 2027 | AF1: 2027 | AG1: 2027 | AH1: 2027 | AI1: 2027 | AJ1: 2028 | AK1: 2028 | AL1: 2028 | AM1: 2028 | AN1: 2028 | AO1: 2028 | AP1: 2028 | AQ1: 2028 | AR1: 2028 | AS1: 2028
B2: Marzo 2025 | C2: Abril 2025 | D2: Mayo 2025 | E2: Junio 2025 | F2: Julio 2025 | G2: Agosto 2025 | H2: Septiembre 2025 | I2: Octubre 2025 | J2: Noviembre 2025 | K2: Diciembre 2025 | L2: Enero 2026 | M2: Febrero 2026 | N2: Marzo 2026 | O2: Abril 2026 | P2: Mayo 2026 | Q2: Junio 2026 | R2: Julio 2026 | S2: Agosto 2026 | T2: Septiembre 2026 | U2: Octubre 2026 | V2: Noviembre 2026 | W2: Diciembre 2026 | X2: Enero 2027 | Y2: Febrero 2027 | Z2: Marzo 2027 | AA2: Abril 2027 | AB2: Mayo 2027 | AC2: Junio 2027 | AD2: Julio 2027 | AE2: Agosto 2027 | AF2: Septiembre 2027 | AG2: Octubre 2027 | AH2: Noviembre 2027 | AI2: Diciembre 2027 | AJ2: Enero 2028 | AK2: Febrero 2028 | AL2: Marzo 2028 | AM2: Abril 2028 | AN2: Mayo 2028 | AO2: Junio 2028 | AP2: Julio 2028 | AQ2: Agosto 2028 | AR2: Septiembre 2028 | AS2: Octubre 2028
A3: 🎓 GASTOS PERSONALES
A4: Materias Abi | B4: 0 | C4: 0 | D4: 0 | E4: 0 | F4: 0 | G4: 0 | H4: 0 | I4: 0 | J4: 0 | K4: 0 | L4: 0 | M4: 0 | N4: 0 | O4: 0 | P4: 0 | Q4: 0 | R4: 0 | S4: 0 | T4: 0 | U4: 0 | V4: 0 | W4: 0 | X4: 0 | Y4: 0 | Z4: 0 | AA4: 0 | AB4: 0 | AC4: 0 | AD4: 0 | AE4: 0 | AF4: 0 | AG4: 0 | AH4: 0 | AI4: 0 | AJ4: 0 | AK4: 0 | AL4: 0 | AM4: 0 | AN4: 0 | AO4: 0 | AP4: 0 | AQ4: 0 | AR4: 0 | AS4: 0
A5: Materias Franco | B5: 0 | C5: 0 | D5: 0 | E5: 0 | F5: 0 | G5: 0 | H5: 0 | I5: 0 | J5: 0 | K5: 0 | L5: 0 | M5: 0 | N5: 0 | O5: 0 | P5: 0 | Q5: 0 | R5: 0 | S5: -30000 | T5: 0 | U5: 0 | V5: 0 | W5: 0 | X5: 0 | Y5: 0 | Z5: 0 | AA5: 0 | AB5: 0 | AC5: 0 | AD5: 0 | AE5: 0 | AF5: 0 | AG5: 0 | AH5: 0 | AI5: 0 | AJ5: 0 | AK5: 0 | AL5: 0 | AM5: 0 | AN5: 0 | AO5: 0 | AP5: 0 | AQ5: 0 | AR5: 0 | AS5: 0
A6: Gimnasio Franco | B6: 0 | C6: 0 | D6: 0 | E6: 0 | F6: 0 | G6: 0 | H6: 0 | I6: -35000 | J6: 0 | K6: 0 | L6: 0 | M6: -39000 | N6: -39000 | O6: 0 | P6: 0 | Q6: 0 | R6: 0 | X6: 0 | Y6: 0 | Z6: 0 | AA6: 0 | AB6: 0 | AC6: 0 | AD6: 0 | AE6: 0 | AF6: 0 | AG6: 0 | AH6: 0 | AI6: 0 | AJ6: 0 | AK6: 0 | AL6: 0 | AM6: 0 | AN6: 0 | AO6: 0 | AP6: 0 | AQ6: 0 | AR6: 0 | AS6: 0
A7: Gimnasio Abi | B7: 0 | C7: 0 | D7: 0 | E7: 0 | F7: 0 | G7: 0 | H7: 0 | I7: -35000 | J7: 0 | K7: 0 | L7: 0 | M7: 0 | N7: 0 | O7: 0 | P7: 0 | Q7: 0 | R7: 0 | S7: 0 | T7: 0 | U7: 0 | V7: 0 | W7: 0 | X7: 0 | Y7: 0 | Z7: 0 | AA7: 0 | AB7: 0 | AC7: 0 | AD7: 0 | AE7: 0 | AF7: 0 | AG7: 0 | AH7: 0 | AI7: 0 | AJ7: 0 | AK7: 0 | AL7: 0 | AM7: 0 | AN7: 0 | AO7: 0 | AP7: 0 | AQ7: 0 | AR7: 0 | AS7: 0
A8: Facultad Franco | B8: 0 | C8: 0 | D8: 0 | E8: 0 | F8: 0 | G8: 0 | H8: 0 | I8: 0 | J8: 0 | K8: 0 | L8: 0 | M8: 0 | N8: 0 | O8: 0 | P8: 0 | Q8: 0 | R8: 0 | S8: 0 | T8: 0 | U8: 0 | V8: 0 | W8: 0 | X8: 0 | Y8: 0 | Z8: 0 | AA8: 0 | AB8: 0 | AC8: 0 | AD8: 0 | AE8: 0 | AF8: 0 | AG8: 0 | AH8: 0 | AI8: 0 | AJ8: 0 | AK8: 0 | AL8: 0 | AM8: 0 | AN8: 0 | AO8: 0 | AP8: 0 | AQ8: 0 | AR8: 0 | AS8: 0
A9: Facultad Abi | B9: 0 | C9: 0 | D9: 0 | E9: 0 | F9: 0 | G9: 0 | H9: 0 | I9: 0 | J9: 0 | K9: 0 | L9: 0 | M9: 0 | N9: 0 | O9: 0 | P9: 0 | Q9: -180000 | R9: -180000 | S9: -360000 | T9: -390000 | U9: -195000 | V9: -195000 | W9: -200000 | X9: -200000 | Y9: -200000 | Z9: -200000 | AA9: -200000 | AB9: -200000 | AC9: -200000 | AD9: 0 | AE9: 0 | AF9: 0 | AG9: 0 | AH9: 0 | AI9: 0 | AJ9: 0 | AK9: 0 | AL9: 0 | AM9: 0 | AN9: 0 | AO9: 0 | AP9: 0 | AQ9: 0 | AR9: 0 | AS9: 0
A10: Ciudadania Franco | V10: -650000 | Z10: -400000
A11: TOTAL | B11: =SUM(B4:B10) -> 0 | C11: =SUM(C4:C10) -> 0 | D11: =SUM(D4:D10) -> 0 | E11: =SUM(E4:E10) -> 0 | F11: =SUM(F4:F10) -> 0 | G11: =SUM(G4:G10) -> 0 | H11: =SUM(H4:H10) -> 0 | I11: =SUM(I4:I10) -> -70000 | ... AS11: =SUM(AS4:AS10) -> 0

Sheet Hogar
B1: 2025 | C1: 2025 | D1: 2025 | E1: 2025 | F1: 2025 | G1: 2025 | H1: 2025 | I1: 2025 | J1: 2025 | K1: 2025 | L1: 2026 | M1: 2026 | N1: 2026 | O1: 2026 | P1: 2026 | Q1: 2026 | R1: 2026 | S1: 2026 | T1: 2026 | U1: 2026 | V1: 2026 | W1: 2026 | X1: 2027 | Y1: 2027 | Z1: 2027 | AA1: 2027 | AB1: 2027 | AC1: 2027 | AD1: 2027 | AE1: 2027 | AF1: 2027 | AG1: 2027 | AH1: 2027 | AI1: 2027 | AJ1: 2028 | AK1: 2028 | AL1: 2028 | AM1: 2028 | AN1: 2028 | AO1: 2028 | AP1: 2028 | AQ1: 2028 | AR1: 2028 | AS1: 2028
B2: Marzo 2025 | C2: Abril 2025 | D2: Mayo 2025 | E2: Junio 2025 | F2: Julio 2025 | G2: Agosto 2025 | H2: Septiembre 2025 | I2: Octubre 2025 | J2: Noviembre 2025 | K2: Diciembre 2025 | L2: Enero 2026 | M2: Febrero 2026 | N2: Marzo 2026 | O2: Abril 2026 | P2: Mayo 2026 | Q2: Junio 2026 | R2: Julio 2026 | S2: Agosto 2026 | T2: Septiembre 2026 | U2: Octubre 2026 | V2: Noviembre 2026 | W2: Diciembre 2026 | X2: Enero 2027 | Y2: Febrero 2027 | Z2: Marzo 2027 | AA2: Abril 2027 | AB2: Mayo 2027 | AC2: Junio 2027 | AD2: Julio 2027 | AE2: Agosto 2027 | AF2: Septiembre 2027 | AG2: Octubre 2027 | AH2: Noviembre 2027 | AI2: Diciembre 2027 | AJ2: Enero 2028 | AK2: Febrero 2028 | AL2: Marzo 2028 | AM2: Abril 2028 | AN2: Mayo 2028 | AO2: Junio 2028 | AP2: Julio 2028 | AQ2: Agosto 2028 | AR2: Septiembre 2028 | AS2: Octubre 2028
A3: 🏠 GASTOS DEL HOGAR
A4: Internet | B4: 0 | C4: 0 | D4: 0 | E4: -24000 | F4: -24000 | G4: -31200 | H4: -58500 | I4: -31200 | J4: -31200 | K4: -32500 | L4: -35000 | M4: -35000 | N4: -35000 | O4: -35000 | P4: -35000 | R4: -36700 | S4: -37109 | T4: -37676 | U4: -37676 | V4: -37676 | W4: -37676 | X4: -37676 | Y4: -37676 | Z4: -37676 | AA4: -37676 | AB4: -37676 | AC4: -37676 | AD4: 0 | AE4: 0 | AF4: 0 | AG4: 0 | AH4: 0 | AI4: 0 | AJ4: 0 | AK4: 0 | AL4: 0 | AM4: 0 | AN4: 0 | AO4: 0 | AP4: 0 | AQ4: 0 | AR4: 0 | AS4: 0
A5: Expensas | B5: 0 | C5: 0 | D5: 0 | E5: 0 | F5: -223000 | G5: -200000 | H5: -161000 | I5: -200000 | J5: -206100 | K5: -200000 | L5: -200000 | M5: -220000 | N5: -220000 | O5: -170000 | P5: -170000 | Q5: -170000 | R5: -167000 | S5: -168000 | T5: -174000 | U5: -174000 | V5: -175000 | W5: -175000 | X5: -175000 | Y5: -175000 | Z5: -175000 | AA5: -175000 | AB5: -175000 | AC5: -175000 | AD5: 0 | AE5: 0 | AF5: 0 | AG5: 0 | AH5: 0 | AI5: 0 | AJ5: 0 | AK5: 0 | AL5: 0 | AM5: 0 | AN5: 0 | AO5: 0 | AP5: 0 | AQ5: 0 | AR5: 0 | AS5: 0
A6: Electricidad | B6: 0 | C6: 0 | D6: 0 | E6: 0 | F6: 0 | G6: 0 | H6: -136300 | I6: -97000 | J6: -79000 | K6: -100000 | L6: -87000 | M6: -89000 | N6: -100000 | O6: -98000 | P6: -109000 | Q6: -110000 | R6: -140000 | S6: -98000 | T6: -122000 | U6: -126000 | V6: -110000 | W6: -110000 | X6: -110000 | Y6: -110000 | Z6: -110000 | AA6: -110000 | AB6: -110000 | AC6: -110000 | AD6: 0 | AE6: 0 | AF6: 0 | AG6: 0 | AH6: 0 | AI6: 0 | AJ6: 0 | AK6: 0 | AL6: 0 | AM6: 0 | AN6: 0 | AO6: 0 | AP6: 0 | AQ6: 0 | AR6: 0 | AS6: 0
A7: Cuenta Corriente | B7: 0 | C7: 0 | D7: 0 | E7: 0 | F7: 0 | G7: 0 | H7: -75000 | I7: -70000 | J7: -75000 | K7: -100000 | L7: 0 | M7: 0 | N7: 0 | O7: 0 | P7: 0 | Q7: 0 | R7: 0 | S7: 0 | T7: 0 | U7: 0 | V7: 0 | W7: 0 | X7: 0 | Y7: 0 | Z7: 0 | AA7: 0 | AB7: 0 | AC7: 0 | AD7: 0 | AE7: 0 | AF7: 0 | AG7: 0 | AH7: 0 | AI7: 0 | AJ7: 0 | AK7: 0 | AL7: 0 | AM7: 0 | AN7: 0 | AO7: 0 | AP7: 0 | AQ7: 0 | AR7: 0 | AS7: 0
A8: Línea Celular | B8: 0 | C8: 0 | D8: 0 | E8: 0 | F8: 0 | G8: 0 | H8: 0 | I8: -21000 | J8: -18000 | K8: -18000 | L8: -18000 | M8: -20000 | N8: -22000 | O8: -21000 | P8: -21000 | Q8: -27880 | R8: -27880 | S8: -29950 | T8: -30666 | U8: -30666 | V8: -30666 | W8: -30666 | X8: -30666 | Y8: -30666 | Z8: -30666 | AA8: -30666 | AB8: -30666 | AC8: -30666 | AD8: 0 | AE8: 0 | AF8: 0 | AG8: 0 | AH8: 0 | AI8: 0 | AJ8: 0 | AK8: 0 | AL8: 0 | AM8: 0 | AN8: 0 | AO8: 0 | AP8: 0 | AQ8: 0 | AR8: 0 | AS8: 0
A9: Transporte | B9: 0 | C9: 0 | D9: 0 | E9: 0 | F9: 0 | G9: 0 | H9: 0 | I9: 0 | J9: 0 | K9: 0 | L9: 0 | M9: -89600 | N9: 0 | O9: 0 | P9: 0 | Q9: 0 | R9: 0 | S9: - | T9: 0 | U9: 0 | V9: 0 | W9: 0 | X9: 0 | Y9: 0 | Z9: 0 | AA9: 0 | AB9: 0 | AC9: 0 | AD9: 0 | AE9: 0 | AF9: 0 | AG9: 0 | AH9: 0 | AI9: 0 | AJ9: 0 | AK9: 0 | AL9: 0 | AM9: 0 | AN9: 0 | AO9: 0 | AP9: 0 | AQ9: 0 | AR9: 0 | AS9: 0
A10: Impuesto Municipal | B10: 0 | C10: 0 | D10: 0 | E10: 0 | F10: 0 | G10: 0 | H10: 0 | I10: 0 | J10: 0 | K10: 0 | L10: 0 | M10: 0 | N10: -55804 | O10: -18601.26 | P10: -18601.26 | Q10: -18601.26 | R10: -18601.26 | S10: -18601.26 | T10: -18601.26 | U10: -18601.26 | V10: -18601.26 | W10: -18601.26 | X10: -18601.26 | Y10: -18601.26 | Z10: -18601.26 | AA10: -18601.26 | AB10: -18601.26 | AC10: -18601.26 | AD10: 0 | AE10: 0 | AF10: 0 | AG10: 0 | AH10: 0 | AI10: 0 | AJ10: 0 | AK10: 0 | AL10: 0 | AM10: 0 | AN10: 0 | AO10: 0 | AP10: 0 | AQ10: 0 | AR10: 0 | AS10: 0
A11: Alquier (Agua y Cloaca) | B11: 0 | C11: 0 | D11: 0 | E11: 0 | F11: 0 | G11: 0 | H11: 0 | I11: 0 | J11: 0 | K11: 0 | L11: -32000 | M11: -34000 | N11: -35000 | O11: -35000 | P11: -35000 | Q11: -35000 | R11: -37000 | S11: -37000 | T11: -37000 | U11: -38000 | V11: -38000 | W11: -39000 | X11: -39000 | Y11: -40000 | Z11: -40000 | AA11: -41000 | AB11: -41000 | AC11: -42000 | AD11: 0 | AE11: 0 | AF11: 0 | AG11: 0 | AH11: 0 | AI11: 0 | AJ11: 0 | AK11: 0 | AL11: 0 | AM11: 0 | AN11: 0 | AO11: 0 | AP11: 0 | AQ11: 0 | AR11: 0 | AS11: 0
A12: Alquiler | B12: 0 | C12: 0 | D12: 0 | E12: 0 | F12: -380000 | G12: -380000 | H12: -380000 | I12: -402860 | J12: -402860 | K12: -402860 | L12: -435000 | M12: -435000 | N12: -435000 | O12: -470000 | P12: -470000 | Q12: -470000 | R12: -505000 | S12: -505000 | T12: -505000 | U12: -535000 | V12: -535000 | W12: -535000 | X12: -562000 | Y12: -562000 | Z12: -562000 | AA12: -592000 | AB12: -592000 | AC12: -592000 | AD12: 0 | AE12: 0 | AF12: 0 | AG12: 0 | AH12: 0 | AI12: 0 | AJ12: 0 | AK12: 0 | AL12: 0 | AM12: 0 | AN12: 0 | AO12: 0 | AP12: 0 | AQ12: 0 | AR12: 0 | AS12: 0
A13: Estacionamiento | B13: 0 | C13: 0 | D13: 0 | E13: 0 | F13: 0 | G13: 0 | H13: 0 | I13: 0 | J13: 0 | K13: 0 | L13: 0 | M13: 0 | N13: 0 | O13: 0 | P13: 0 | Q13: 0 | R13: 0 | S13: 0 | T13: 0 | U13: 0 | V13: 0 | W13: 0 | X13: 0 | Y13: 0 | Z13: 0 | AA13: 0 | AB13: 0 | AC13: 0 | AD13: 0 | AE13: 0 | AF13: 0 | AG13: 0 | AH13: 0 | AI13: 0 | AJ13: 0 | AK13: 0 | AL13: 0 | AM13: 0 | AN13: 0 | AO13: 0 | AP13: 0 | AQ13: 0 | AR13: 0 | AS13: 0
A14: Seguro | B14: 0 | C14: 0 | D14: 0 | E14: 0 | F14: 0 | G14: 0 | H14: 0 | I14: 0 | J14: 0 | K14: 0 | L14: 0 | M14: 0 | N14: 0 | O14: 0 | P14: 0 | Q14: 0 | R14: 0 | S14: 0 | T14: 0 | U14: 0 | V14: 0 | W14: 0 | X14: 0 | Y14: 0 | Z14: 0 | AA14: 0 | AB14: 0 | AC14: 0 | AD14: 0 | AE14: 0 | AF14: 0 | AG14: 0 | AH14: 0 | AI14: 0 | AJ14: 0 | AK14: 0 | AL14: 0 | AM14: 0 | AN14: 0 | AO14: 0 | AP14: 0 | AQ14: 0 | AR14: 0 | AS14: 0
A15: Rentas | B15: 0 | C15: 0 | D15: 0 | E15: 0 | F15: 0 | G15: 0 | H15: 0 | I15: 0 | J15: 0 | K15: 0 | L15: 0 | M15: 0 | N15: 0 | O15: 0 | P15: 0 | Q15: 0 | R15: 0 | S15: 0 | T15: 0 | U15: 0 | V15: 0 | W15: 0 | X15: 0 | Y15: 0 | Z15: 0 | AA15: 0 | AB15: 0 | AC15: 0 | AD15: 0 | AE15: 0 | AF15: 0 | AG15: 0 | AH15: 0 | AI15: 0 | AJ15: 0 | AK15: 0 | AL15: 0 | AM15: 0 | AN15: 0 | AO15: 0 | AP15: 0 | AQ15: 0 | AR15: 0 | AS15: 0
A16: TOTAL | B16: =SUM(B4:B12) -> 0 | C16: =SUM(C4:C12) -> 0 | D16: =SUM(D4:D12) -> 0 | E16: =SUM(E4:E12) -> -24000 | F16: =SUM(F4:F12) -> -627000 | G16: =SUM(G4:G12) -> -611200 | H16: =SUM(H4:H12) -> -810800 | I16: =SUM(I4:I12) -> -822060 | ... S16: =SUM(S4:S12) -> -893660.26 | T16: =SUM(T4:T15) -> -924943.26 | U16: =SUM(U4:U15) -> -959943.26 | V16: =SUM(V4:V15) -> -944943.26 | W16: =SUM(W4:W15) -> -945943.26 | X16: =SUM(X4:X15) -> -972943.26 | Y16: =SUM(Y4:Y15) -> -973943.26 | Z16: =SUM(Z4:Z15) -> -973943.26 | AA16: =SUM(AA4:AA15) -> -1004943.3 | ... AC16: =SUM(AC4:AC15) -> -1005943.3 | AD16: =SUM(AD4:AD12) -> 0 | AE16: =SUM(AE4:AE12) -> 0 | AF16: =SUM(AF4:AF12) -> 0 | AG16: =SUM(AG4:AG12) -> 0 | AH16: =SUM(AH4:AH12) -> 0 | AI16: =SUM(AI4:AI12) -> 0 | AJ16: =SUM(AJ4:AJ12) -> 0 | AK16: =SUM(AK4:AK12) -> 0 | ... AS16: =SUM(AS4:AS12) -> 0

Sheet Deudas_Varios
B1: 2025 | C1: 2025 | D1: 2025 | E1: 2025 | F1: 2025 | G1: 2025 | H1: 2025 | I1: 2025 | J1: 2025 | K1: 2025 | L1: 2026 | M1: 2026 | N1: 2026 | O1: 2026 | P1: 2026 | Q1: 2026 | R1: 2026 | S1: 2026 | T1: 2026 | U1: 2026 | V1: 2026 | W1: 2026 | X1: 2027 | Y1: 2027 | Z1: 2027 | AA1: 2027 | AB1: 2027 | AC1: 2027 | AD1: 2027 | AE1: 2027 | AF1: 2027 | AG1: 2027 | AH1: 2027 | AI1: 2027 | AJ1: 2028 | AK1: 2028 | AL1: 2028 | AM1: 2028 | AN1: 2028 | AO1: 2028 | AP1: 2028 | AQ1: 2028 | AR1: 2028 | AS1: 2028
B2: Marzo 2025 | C2: Abril 2025 | D2: Mayo 2025 | E2: Junio 2025 | F2: Julio 2025 | G2: Agosto 2025 | H2: Septiembre 2025 | I2: Octubre 2025 | J2: Noviembre 2025 | K2: Diciembre 2025 | L2: Enero 2026 | M2: Febrero 2026 | N2: Marzo 2026 | O2: Abril 2026 | P2: Mayo 2026 | Q2: Junio 2026 | R2: Julio 2026 | S2: Agosto 2026 | T2: Septiembre 2026 | U2: Octubre 2026 | V2: Noviembre 2026 | W2: Diciembre 2026 | X2: Enero 2027 | Y2: Febrero 2027 | Z2: Marzo 2027 | AA2: Abril 2027 | AB2: Mayo 2027 | AC2: Junio 2027 | AD2: Julio 2027 | AE2: Agosto 2027 | AF2: Septiembre 2027 | AG2: Octubre 2027 | AH2: Noviembre 2027 | AI2: Diciembre 2027 | AJ2: Enero 2028 | AK2: Febrero 2028 | AL2: Marzo 2028 | AM2: Abril 2028 | AN2: Mayo 2028 | AO2: Junio 2028 | AP2: Julio 2028 | AQ2: Agosto 2028 | AR2: Septiembre 2028 | AS2: Octubre 2028
A3: 📋 DEUDAS & GASTOS VARIOS
A4: Papá | B4: 0 | C4: 0 | D4: 0 | E4: 0 | F4: 0 | G4: 0 | H4: 0 | I4: 0 | J4: 0 | K4: -50000 | L4: 0 | M4: 0 | N4: 0 | O4: 0 | P4: 0 | Q4: 0 | R4: 0 | S4: 0 | T4: 0 | U4: 0 | V4: 0 | W4: 0 | X4: 0 | Y4: 0 | Z4: 0 | AA4: 0 | AB4: 0 | AC4: 0 | AD4: 0 | AE4: 0 | AF4: 0 | AG4: 0 | AH4: 0 | AI4: 0 | AJ4: 0 | AK4: 0 | AL4: 0 | AM4: 0 | AN4: 0 | AO4: 0 | AP4: 0 | AQ4: 0 | AR4: 0 | AS4: 0
A5: Juani | B5: 0 | C5: 0 | D5: 0 | E5: 0 | F5: 0 | G5: 0 | H5: 0 | I5: 0 | J5: 0 | K5: -250000 | L5: 0 | M5: 0 | N5: 0 | O5: 0 | P5: 0 | Q5: 0 | R5: 0 | S5: 0 | T5: 0 | U5: 0 | V5: 0 | W5: 0 | X5: 0 | Y5: 0 | Z5: -400000 | AA5: 0 | AB5: 0 | AC5: 0 | AD5: 0 | AE5: 0 | AF5: 0 | AG5: 0 | AH5: 0 | AI5: 0 | AJ5: 0 | AK5: 0 | AL5: 0 | AM5: 0 | AN5: 0 | AO5: 0 | AP5: 0 | AQ5: 0 | AR5: 0 | AS5: 0
A6: Gastos Comida | B6: 0 | C6: 0 | D6: 0 | E6: 0 | F6: 0 | G6: 0 | H6: 0 | I6: 0 | J6: 0 | K6: 0 | L6: 0 | M6: -492399 | N6: -684195 | O6: 0 | P6: 0 | R6: 0 | S6: 0 | T6: 0 | U6: 0 | V6: 0 | W6: 0 | X6: 0 | Y6: 0 | Z6: 0 | AA6: 0 | AB6: 0 | AC6: 0 | AD6: 0 | AE6: 0 | AF6: 0 | AG6: 0 | AH6: 0 | AI6: 0 | AJ6: 0 | AK6: 0 | AL6: 0 | AM6: 0 | AN6: 0 | AO6: 0 | AP6: 0 | AQ6: 0 | AR6: 0 | AS6: 0
A7: Entradas a casamiento | B7: 0 | C7: 0 | D7: 0 | E7: 0 | F7: 0 | G7: 0 | H7: 0 | I7: 0 | J7: 0 | K7: 0 | L7: 0 | M7: 0 | N7: 0 | O7: 0 | P7: 0 | Q7: 0 | R7: 0 | T7: -200000 | U7: 0 | V7: 0 | W7: 0 | X7: 0 | Y7: 0 | Z7: 0 | AA7: 0 | AB7: 0 | AC7: 0 | AD7: 0 | AE7: 0 | AF7: 0 | AG7: 0 | AH7: 0 | AI7: 0 | AJ7: 0 | AK7: 0 | AL7: 0 | AM7: 0 | AN7: 0 | AO7: 0 | AP7: 0 | AQ7: 0 | AR7: 0 | AS7: 0
A8: Gastos Varios | B8: 0 | C8: 0 | D8: 0 | E8: 0 | F8: 0 | G8: 0 | H8: 0 | I8: 0 | J8: 0 | K8: 0 | L8: 0 | M8: 0 | N8: 0 | O8: 0 | P8: 0 | Q8: -85000 | R8: -70000 | S8: -70000 | T8: -70000 | U8: -70000 | V8: -70000 | W8: 0 | X8: 0 | Y8: 0 | Z8: 0 | AA8: 0 | AB8: 0 | AC8: 0 | AD8: 0 | AE8: 0 | AF8: 0 | AG8: 0 | AH8: 0 | AI8: 0 | AJ8: 0 | AK8: 0 | AL8: 0 | AM8: 0 | AN8: 0 | AO8: 0 | AP8: 0 | AQ8: 0 | AR8: 0 | AS8: 0
A9: Mes adelantado + % contrato | B9: 0 | C9: 0 | D9: 0 | E9: 0 | F9: -760000 | G9: 0 | H9: 0 | I9: 0 | J9: 0 | K9: 0 | L9: 0 | M9: 0 | N9: 0 | O9: 0 | P9: 0 | Q9: 0 | R9: 0 | S9: 0 | T9: 0 | U9: 0 | V9: 0 | W9: 0 | X9: - | Y9: 0 | Z9: 0 | AA9: 0 | AB9: 0 | AC9: 0 | AD9: 0 | AE9: 0 | AF9: 0 | AG9: 0 | AH9: 0 | AI9: 0 | AJ9: 0 | AK9: 0 | AL9: 0 | AM9: 0 | AN9: 0 | AO9: 0 | AP9: 0 | AQ9: 0 | AR9: 0 | AS9: 0
A10: Diferencias de deudas
A11: TOTAL | B11: =SUM(B4:B9) -> 0 | C11: =SUM(C4:C9) -> 0 | D11: =SUM(D4:D9) -> 0 | E11: =SUM(E4:E9) -> 0 | F11: =SUM(F4:F10) -> -760000 | G11: =SUM(G4:G10) -> 0 | H11: =SUM(H4:H10) -> 0 | I11: =SUM(I4:I10) -> 0 | J11: =SUM(J4:J10) -> 0 | K11: =SUM(K4:K10) -> -300000 | L11: =SUM(L4:L10) -> 0 | M11: =SUM(M4:M10) -> -492399 | ... AS11: =SUM(AS4:AS10) -> 0

Sheet Referencia
A1: 📌 DATOS DE REFERENCIA - ALQUILERES
A2: Concepto | B2: Alquiler Actual | C2: Alquiler E. Vieja | D2: Diferencia

Sheet Objetivos
A1: 🎯 PLAN DE OBJETIVOS FINANCIEROS — SECUENCIAL
A2: 📐 SUPUESTO: Ahorro mensual destinado a objetivos
A3: Ahorro mensual ($) | B3: 200000 | C3: ← Modificar cada mes según tu ahorro real
A5: OBJETIVO | B5: PRIORIDAD | C5: FECHA LIMITE | D5: MONTO META ($) | E5: YA AHORRADO ($) | F5: FALTANTE ($) | G5: % AVANCE | H5: MESES RESTANTES | I5: ESTADO
A6: CIUDADANÍA (TRADUCCIÓN) | B6: 1 | C6: nov-26 | D6: 650000 | E6: 0 | F6: =IF(D6=0,"-",D6-E6) -> 650000 | G6: =IF(D6=0,"-",E6/D6) -> 0 | H6: =IF(D6=0,"-",IF(E6>=D6,0,CEILING((D6-E6)/$B$3,1))) -> 4 | I6: =IF(D6=0,"N/A",IF(E6>=D6,"✅ LISTO",IF(E6/D6>=0.5,"🟡 EN CURSO","🔴 PENDIENTE"))) -> 🔴 PENDIENTE
A7: CIUDADANÍA (EMBAJADA) | B7: 2 | C7: mar-27 | D7: 650000 | E7: 0 | F7: =IF(D7=0,"-",D7-E7) -> 650000 | G7: =IF(D7=0,"-",E7/D7) -> 0 | H7: =IF(D7=0,"-",IF(E7>=D7,0,F6/$B$3+CEILING((D7-E7)/$B$3,1))) -> 7.25 | I7: =IF(D7=0,"N/A",IF(E7>=D7,"✅ LISTO",IF(E7/D7>=0.5,"🟡 EN CURSO","🔴 PENDIENTE"))) -> 🔴 PENDIENTE
A8: INVERSIÓN S&P 500 | B8: 3 | C8: Sin fecha | D8: 0 | E8: 0 | F8: =IF(D8=0,"-",D8-E8) -> - | G8: =IF(D8=0,"-",E8/D8) -> - | H8: "-" | I8: =IF(E8>0,"💰 INVIRTIENDO","⏳ PRÓXIMO") -> ⏳ PRÓXIMO
A9: TOTAL OBJETIVOS FIJOS | D9: =D6+D7 -> 1300000 | E9: =E6+E7 -> 0 | F9: =F6+F7 -> 1300000
A11: 📋 LÓGICA SECUENCIAL
A12: 1. Ahorrás $200.000/mes → Traducción cubierta en ~2-3 meses (nov-26)
A13: 2. Pagada la Traducción en nov-26 → seguís ahorrando $200.000/mes → Embajada cubierta en mar-27
A14: 3. Cumplidos ambos objetivos → el ahorro mensual se destina libre a Inversión S&P 500
